doc_classifier/__init__.py
doc_classifier/doc_classifier.py
doc_classifier/data/doc_classifier.pkl
doc_classifier-0.0.9.dist-info/LICENSE.md
doc_classifier-0.0.9.dist-info/METADATA
doc_classifier-0.0.9.dist-info/WHEEL
doc_classifier-0.0.9.dist-info/top_level.txt
doc_classifier-0.0.9.dist-info/RECORD
