Metadata-Version: 2.1
Name: doc-classifier
Version: 0.0.9
Summary: A package to classify scientific documents by field of study
Home-page: https://github.com/amira-codecamp/doc-classifier
Author: amira-codecamp
Classifier: Programming Language :: Python
Classifier: Programming Language :: Python :: 3
Classifier: Programming Language :: Python :: 3.9
License-File: LICENSE.md
Requires-Dist: arabic-reshaper
Requires-Dist: joblib
Requires-Dist: nltk
Requires-Dist: scikit-learn (==1.0.2)
